[{"id":1,"nome":"UTI Adulto","representanteId":1,"representante":null,"estabelecimentoId":1,"estabelecimento":null},{"id":2,"nome":"Pronto Socorro","representanteId":2,"representante":null,"estabelecimentoId":2,"estabelecimento":null},{"id":3,"nome":"Pediatria","representanteId":3,"representante":null,"estabelecimentoId":3,"estabelecimento":null},{"id":4,"nome":"Centro Cirúrgico","representanteId":4,"representante":null,"estabelecimentoId":4,"estabelecimento":null},{"id":5,"nome":"Clínica Médica","representanteId":5,"representante":null,"estabelecimentoId":5,"estabelecimento":null},{"id":6,"nome":"Setor Teste 1","representanteId":1,"representante":null,"estabelecimentoId":1,"estabelecimento":null},{"id":7,"nome":"Setor Teste 2","representanteId":2,"representante":null,"estabelecimentoId":2,"estabelecimento":null},{"id":8,"nome":"Setor Teste 3","representanteId":3,"representante":null,"estabelecimentoId":3,"estabelecimento":null},{"id":9,"nome":"Setor Teste 4","representanteId":4,"representante":null,"estabelecimentoId":4,"estabelecimento":null},{"id":10,"nome":"Setor Teste 5","representanteId":5,"representante":null,"estabelecimentoId":5,"estabelecimento":null},{"id":11,"nome":"Setor Teste 6","representanteId":1,"representante":null,"estabelecimentoId":1,"estabelecimento":null},{"id":12,"nome":"Setor Teste 7","representanteId":2,"representante":null,"estabelecimentoId":2,"estabelecimento":null},{"id":13,"nome":"Setor Teste 8","representanteId":3,"representante":null,"estabelecimentoId":3,"estabelecimento":null},{"id":14,"nome":"Setor Teste 9","representanteId":4,"representante":null,"estabelecimentoId":4,"estabelecimento":null},{"id":15,"nome":"Setor Teste 10","representanteId":5,"representante":null,"estabelecimentoId":5,"estabelecimento":null},{"id":16,"nome":"Setor Teste 11","representanteId":1,"representante":null,"estabelecimentoId":1,"estabelecimento":null},{"id":17,"nome":"Setor Teste 12","representanteId":2,"representante":null,"estabelecimentoId":2,"estabelecimento":null},{"id":18,"nome":"Setor Teste 13","representanteId":3,"representante":null,"estabelecimentoId":3,"estabelecimento":null},{"id":19,"nome":"Setor Teste 14","representanteId":4,"representante":null,"estabelecimentoId":4,"estabelecimento":null},{"id":20,"nome":"Setor Teste 15","representanteId":5,"representante":null,"estabelecimentoId":5,"estabelecimento":null},{"id":21,"nome":"Setor Teste 16","representanteId":1,"representante":null,"estabelecimentoId":1,"estabelecimento":null},{"id":22,"nome":"Setor Teste 17","representanteId":2,"representante":null,"estabelecimentoId":2,"estabelecimento":null},{"id":23,"nome":"Setor Teste 18","representanteId":3,"representante":null,"estabelecimentoId":3,"estabelecimento":null},{"id":24,"nome":"Setor Teste 19","representanteId":4,"representante":null,"estabelecimentoId":4,"estabelecimento":null},{"id":25,"nome":"Setor Teste 20","representanteId":5,"representante":null,"estabelecimentoId":5,"estabelecimento":null}]